odoo/addons/pos_sale_product_config_no_variant/README.rst
odoo/addons/pos_sale_product_config_no_variant/__init__.py
odoo/addons/pos_sale_product_config_no_variant/__manifest__.py
odoo/addons/pos_sale_product_config_no_variant/i18n/es.po
odoo/addons/pos_sale_product_config_no_variant/i18n/it.po
odoo/addons/pos_sale_product_config_no_variant/i18n/pos_sale_product_config_no_variant.pot
odoo/addons/pos_sale_product_config_no_variant/models/__init__.py
odoo/addons/pos_sale_product_config_no_variant/models/pos_order.py
odoo/addons/pos_sale_product_config_no_variant/models/pos_order_line.py
odoo/addons/pos_sale_product_config_no_variant/models/pos_session.py
odoo/addons/pos_sale_product_config_no_variant/readme/CONTRIBUTORS.rst
odoo/addons/pos_sale_product_config_no_variant/readme/CREDITS.rst
odoo/addons/pos_sale_product_config_no_variant/readme/DESCRIPTION.rst
odoo/addons/pos_sale_product_config_no_variant/readme/USAGE.rst
odoo/addons/pos_sale_product_config_no_variant/static/description/icon.png
odoo/addons/pos_sale_product_config_no_variant/static/description/index.html
odoo/addons/pos_sale_product_config_no_variant/static/src/js/OrderLines.js
odoo/addons/pos_sale_product_config_no_variant/static/src/js/PosProductConfig.js
odoo/addons/pos_sale_product_config_no_variant/static/src/js/ProductScreen.js
odoo/addons/pos_sale_product_config_no_variant/views/pos_order_views.xml
odoo_addon_pos_sale_product_config_no_variant-16.0.1.0.1.dist-info/METADATA
odoo_addon_pos_sale_product_config_no_variant-16.0.1.0.1.dist-info/WHEEL
odoo_addon_pos_sale_product_config_no_variant-16.0.1.0.1.dist-info/top_level.txt
odoo_addon_pos_sale_product_config_no_variant-16.0.1.0.1.dist-info/RECORD
