Metadata-Version: 2.1
Name: odoo-addon-pos_sale_product_config_no_variant
Version: 16.0.1.0.1
Summary: Manage Point Of Sale via Configurator of no variant
Home-page: https://github.com/OCA/pos
Author: Open Source Integrators, Odoo Community Association (OCA)
Author-email: support@odoo-community.org
License: AGPL-3
Classifier: Programming Language :: Python
Classifier: Framework :: Odoo
Classifier: Framework :: Odoo :: 16.0
Classifier: License :: OSI Approved :: GNU Affero General Public License v3
Requires-Python: >=3.10
Requires-Dist: odoo<16.1dev,>=16.0a
